pycaruna/__init__.py
pycaruna/authenticator.py
pycaruna/client.py
pycaruna/utils.py
pycaruna-1.0.3.dist-info/LICENSE
pycaruna-1.0.3.dist-info/METADATA
pycaruna-1.0.3.dist-info/WHEEL
pycaruna-1.0.3.dist-info/top_level.txt
pycaruna-1.0.3.dist-info/RECORD
