Metadata-Version: 2.1
Name: pycaruna
Version: 1.0.3
Summary: Caruna API Python implementation
Author-email: Sam Stenvall <neggelandia@gmail.com>
Project-URL: Homepage, https://github.com/Jalle19/pycaruna
Project-URL: Bug Tracker, https://github.com/Jalle19/pycaruna/issues
Classifier: Operating System :: OS Independent
Classifier: Programming Language :: Python :: 3
Requires-Python: >=3.8
License-File: LICENSE
Requires-Dist: beautifulsoup4 >=4.9
Requires-Dist: lxml >=4.6
Requires-Dist: requests >=2
